permutation_no_repetition/README.MD
permutation_no_repetition/__init__.py
permutation_no_repetition/requirements.txt
permutation_no_repetition/thirdparty.json
permutation_no_repetition-0.10.dist-info/LICENSE.rst
permutation_no_repetition-0.10.dist-info/METADATA
permutation_no_repetition-0.10.dist-info/WHEEL
permutation_no_repetition-0.10.dist-info/top_level.txt
permutation_no_repetition-0.10.dist-info/RECORD
