Metadata-Version: 2.1
Name: permutation-no-repetition
Version: 0.10
Summary: Permutation without repetition - written in Cython - for Numpy 
Home-page: https://github.com/hansalemaos/permutation_no_repetition
Author: Johannes Fischer
Author-email: aulasparticularesdealemaosp@gmail.com
License: MIT
Keywords: cython,Permutation
Classifier: Development Status :: 4 - Beta
Classifier: Programming Language :: Python :: 3 :: Only
Classifier: Programming Language :: Python :: 3.10
Classifier: Topic :: Software Development :: Libraries :: Python Modules
Classifier: Topic :: Utilities
License-File: LICENSE.rst
Requires-Dist: Cython
Requires-Dist: numpy
Requires-Dist: zipint
